fastapi_permissions/__init__.py
fastapi_permissions/example.py
fastapi_permissions-0.2.7.dist-info/LICENSE
fastapi_permissions-0.2.7.dist-info/WHEEL
fastapi_permissions-0.2.7.dist-info/METADATA
fastapi_permissions-0.2.7.dist-info/RECORD
