Metadata-Version: 1.1
Name: fastapi_permissions
Version: 0.2.7
Summary: Row Level Permissions for FastAPI
Home-page: https://github.com/holgi/fastapi-permissions
Author: Holger Frey
Author-email: mail@holgerfrey.de
